pgmigrate.py
scaleplan_pgmigrate-1.0.4.1.dist-info/AUTHORS
scaleplan_pgmigrate-1.0.4.1.dist-info/LICENSE
scaleplan_pgmigrate-1.0.4.1.dist-info/METADATA
scaleplan_pgmigrate-1.0.4.1.dist-info/WHEEL
scaleplan_pgmigrate-1.0.4.1.dist-info/entry_points.txt
scaleplan_pgmigrate-1.0.4.1.dist-info/top_level.txt
scaleplan_pgmigrate-1.0.4.1.dist-info/RECORD
